fpiaioact/__init__.py
fpiaioact/actors.py
fpiaioact/app.py
fpiaioact/constants.py
fpiaioact/runners.py
fpiaioact/structures.py
fpiaioact/utils.py
fpiaioact-1.0.3.dist-info/METADATA
fpiaioact-1.0.3.dist-info/WHEEL
fpiaioact-1.0.3.dist-info/RECORD
