Metadata-Version: 2.3
Name: fpiaioact
Version: 1.0.3
Summary: 
Author: Aleksandr Yurlov
Author-email: Sasha.yur@mail.ru
Requires-Python: >=3.12,<4.0
Classifier: Programming Language :: Python :: 3
Classifier: Programming Language :: Python :: 3.12
Classifier: Programming Language :: Python :: 3.13
Requires-Dist: fastapi (>=0.116.1,<0.117.0)
